<?xml version="1.0" encoding="utf-8" ?><dwsync><file name="accepted-elements.html" server="capricorne.sciences-po.fr/news.sciences-po.fr/html/" local="3355465818" remote="11957423732" /><file name="default.html" server="capricorne.sciences-po.fr/news.sciences-po.fr/html/" local="3355465818" remote="11957423732" /><file name="index.html" server="capricorne.sciences-po.fr/news.sciences-po.fr/html/" local="3355465818" remote="11957423792" /><file name="photo-manager.html" server="capricorne.sciences-po.fr/news.sciences-po.fr/html/" local="3363913816" remote="11957423792" /><file name="propagation.html" server="capricorne.sciences-po.fr/news.sciences-po.fr/html/" local="3355465818" remote="11957423792" /><file name="revert.html" server="capricorne.sciences-po.fr/news.sciences-po.fr/html/" local="3355465818" remote="11957423792" /><file name="shopping-cart.html" server="capricorne.sciences-po.fr/news.sciences-po.fr/html/" local="3355465818" remote="11957423792" /><file name="visual-feedback.html" server="capricorne.sciences-po.fr/news.sciences-po.fr/html/" local="3355465818" remote="11957423792" /></dwsync>